[
  {
    "roll": 2,
    "name": "Игуана на палочке",
    "id": "food_iguana_on_stick"
  },
  {
    "roll": 3,
    "name": "Беличьи шашлычки",
    "id": "food_squirrel_stew"
  },
  {
    "roll": 4,
    "name": "Жареная радтараканина",
    "id": "food_radroach"
  },
  {
    "roll": 5,
    "name": "Солсбери-стейк",
    "id": "food_salisbury_steak"
  },
  {
    "roll": 6,
    "name": "Свинина с бобами",
    "id": "food_pork_n_beans"
  },
  {
    "roll": 7,
    "name": "Собачьи консервы",
    "id": "food_canned_dog_food"
  },
  {
    "roll": 8,
    "name": "Кусочки игуаны",
    "id": "food_iguana_bits"
  },
  {
    "roll": 9,
    "name": "Макароны с сыром",
    "id": "food_mac_n_cheese"
  },
  {
    "roll": 10,
    "name": "Засахаренные яблоки",
    "id": "food_apple_candy"
  },
  {
    "roll": 11,
    "name": "Картофельные чипсы",
    "id": "food_potato_chips"
  },
  {
    "roll": 12,
    "name": "Кукуруза",
    "id": "food_corn"
  },
  {
    "roll": 13,
    "name": "Морковь",
    "id": "food_carrot"
  },
  {
    "roll": 14,
    "name": "Тато",
    "id": "food_tato"
  },
  {
    "roll": 15,
    "name": "Дыня",
    "id": "loot_food_дыня"
  },
  {
    "roll": 16,
    "name": "Кусочки белки",
    "id": "loot_food_кусочки_белки"
  },
  {
    "roll": 17,
    "name": "Стейк из брамина",
    "id": "loot_food_стейк_из_брамина"
  },
  {
    "roll": 18,
    "name": "Яйцо болотника",
    "id": "loot_food_яйцо_болотника"
  },
  {
    "roll": 19,
    "name": "Ребрышки яо-гая",
    "id": "loot_food_ребрышки_яо-гая"
  },
  {
    "roll": 20,
    "name": "Стейк из кротокрыса",
    "id": "loot_food_стейк_из_кротокрыса"
  },
  {
    "roll": 21,
    "name": "Мясо болотника",
    "id": "loot_food_мясо_болотника"
  },
  {
    "roll": 22,
    "name": "Мясо жалокрыла",
    "id": "loot_food_мясо_жалокрыла"
  },
  {
    "roll": 23,
    "name": "Мясо гуля",
    "id": "loot_food_мясо_гуля"
  },
  {
    "roll": 24,
    "name": "Человечина",
    "id": "loot_food_человечина"
  },
  {
    "roll": 25,
    "name": "Яйцо когтя смерти",
    "id": "loot_food_яйцо_когтя_смерти"
  },
  {
    "roll": 26,
    "name": "Стейк из когтя смерти",
    "id": "loot_food_стейк_из_когтя_смерти"
  },
  {
    "roll": 27,
    "name": "Странное мясо",
    "id": "loot_food_странное_мясо"
  },
  {
    "roll": 28,
    "name": "Шашлык из странного мяса",
    "id": "loot_food_шашлык_из_странного_мяса"
  },
  {
    "roll": 29,
    "name": "Чистая вода",
    "id": "loot_food_чистая_вода"
  },
  {
    "roll": 30,
    "name": "Грязная вода",
    "id": "loot_food_грязная_вода"
  },
  {
    "roll": 31,
    "name": "Желудь",
    "id": "loot_food_желудь"
  },
  {
    "roll": 32,
    "name": "Молоко брамина",
    "id": "loot_food_молоко_брамина"
  },
  {
    "roll": 33,
    "name": "Бритофрукт",
    "id": "loot_food_бритофрукт"
  },
  {
    "roll": 34,
    "name": "Мутафрукт",
    "id": "loot_food_мутафрукт"
  },
  {
    "roll": 35,
    "name": "Нюка-кола",
    "id": "drink_nuka_cola"
  },
  {
    "roll": 36,
    "name": "Нюка-кола Квантовая",
    "id": "loot_food_нюка-кола_квантовая"
  },
  {
    "roll": 37,
    "name": "Сансет Саспарилла",
    "id": "loot_food_сансет_саспарилла"
  },
  {
    "roll": 38,
    "name": "Пиво",
    "id": "drink_beer"
  },
  {
    "roll": 39,
    "name": "Водка",
    "id": "drink_vodka"
  },
  {
    "roll": 40,
    "name": "Виски",
    "id": "drink_whiskey"
  }
]